https_login/__init__.py
https_login/server.py
https_login-1.3.0.dist-info/licenses/LICENSE
https_login-1.3.0.dist-info/METADATA
https_login-1.3.0.dist-info/WHEEL
https_login-1.3.0.dist-info/entry_points.txt
https_login-1.3.0.dist-info/top_level.txt
https_login-1.3.0.dist-info/RECORD
