Metadata-Version: 2.4
Name: https-login
Version: 1.3.0
Summary: Tiny HTTPS file server (like python -m http.server) with a simple login page and temp self-signed cert.
Author-email: Benjamin Kasser <benjaminkasser@gmail.com>
License: MIT License
Project-URL: Homepage, https://github.com/Nero2201/https-login
Project-URL: Issues, https://github.com/Nero2201/https-login/issues
Keywords: https,httpserver,fileserver,login,python
Requires-Python: >=3.9
License-File: LICENSE
Requires-Dist: cryptography>=41
Dynamic: license-file
